sapp/__init__.py
sapp/config.py
sapp/core.py
sapp/daemon.py
sapp/forms.py
sapp/gpustat.py
sapp/sapp.py
sapp/utils.py
sapp_py-0.5.0.dev1.dist-info/LICENSE
sapp_py-0.5.0.dev1.dist-info/METADATA
sapp_py-0.5.0.dev1.dist-info/WHEEL
sapp_py-0.5.0.dev1.dist-info/entry_points.txt
sapp_py-0.5.0.dev1.dist-info/top_level.txt
sapp_py-0.5.0.dev1.dist-info/RECORD
