Metadata-Version: 2.2
Name: sapp-py
Version: 0.5.0.dev1
Summary: Command helper for slurm system. Act as if you are on compute node.
License: MIT License
Project-URL: Homepage, https://github.com/why-in-Shanghaitech/sapp
Project-URL: Documentation, https://github.com/why-in-Shanghaitech/sapp/blob/master/README.md
Project-URL: Repository, https://github.com/why-in-Shanghaitech/sapp.git
Project-URL: Bug Tracker, https://github.com/why-in-Shanghaitech/sapp/issues
Classifier: Development Status :: 3 - Alpha
Classifier: Programming Language :: Python :: 3 :: Only
Classifier: Operating System :: POSIX :: Linux
Requires-Python: >=3.8
License-File: LICENSE
Requires-Dist: npyscreen>=4.10.5
Requires-Dist: pexpect
Requires-Dist: pyotp
Requires-Dist: filelock
Requires-Dist: slash-py
